ndlapi/__init__.py
ndlapi/__main__.py
ndlapi/api/__init__.py
ndlapi/api/_auth/AuthCredentials.py
ndlapi/api/_auth/SSLCredentials.py
ndlapi/api/_auth/__init__.py
ndlapi/api/_interfaces/ImagesRecognitionService.py
ndlapi/api/_interfaces/RecognitionService.py
ndlapi/api/_interfaces/StreamingService.py
ndlapi/api/_interfaces/VideoRecognitionService.py
ndlapi/api/_interfaces/__init__.py
ndlapi/api/_pyproto/AgeEstimationService_pb2.py
ndlapi/api/_pyproto/AgeEstimationService_pb2_grpc.py
ndlapi/api/_pyproto/BodyTrackerService_pb2.py
ndlapi/api/_pyproto/BodyTrackerService_pb2_grpc.py
ndlapi/api/_pyproto/FaceDetectionService_pb2.py
ndlapi/api/_pyproto/FaceDetectionService_pb2_grpc.py
ndlapi/api/_pyproto/HeartRateService_pb2.py
ndlapi/api/_pyproto/HeartRateService_pb2_grpc.py
ndlapi/api/_pyproto/MultiFrameEmotionService_pb2.py
ndlapi/api/_pyproto/MultiFrameEmotionService_pb2_grpc.py
ndlapi/api/_pyproto/PersonDetectorService_pb2.py
ndlapi/api/_pyproto/PersonDetectorService_pb2_grpc.py
ndlapi/api/_pyproto/SatisfactionIndexService_pb2.py
ndlapi/api/_pyproto/SatisfactionIndexService_pb2_grpc.py
ndlapi/api/_pyproto/SingleFrameEmotionService_pb2.py
ndlapi/api/_pyproto/SingleFrameEmotionService_pb2_grpc.py
ndlapi/api/_pyproto/__init__.py
ndlapi/api/_pyproto/api_common_pb2.py
ndlapi/api/_pyproto/api_common_pb2_grpc.py
ndlapi/api/_services/BodyPoseEstimationService.py
ndlapi/api/_services/EmotionRecognitionService.py
ndlapi/api/_services/FaceDetectorService.py
ndlapi/api/_services/HeartRateService.py
ndlapi/api/_services/MultiModalEmotionRecognition.py
ndlapi/api/_services/PersonDetectorService.py
ndlapi/api/_services/SatisfactionIndexService.py
ndlapi/api/_services/SexAndAgeEstimationService.py
ndlapi/api/_services/__init__.py
ndlapi/api/_utils/__init__.py
ndlapi/api/_utils/error_utils.py
ndlapi/api/_utils/io_utils.py
ndlapi/api/_utils/os_utils.py
ndlapi/process_images/__init__.py
ndlapi/process_images/__main__.py
ndlapi/process_video/__init__.py
ndlapi/process_video/__main__.py
ndl_api-1.1.4.dist-info/LICENSE
ndl_api-1.1.4.dist-info/METADATA
ndl_api-1.1.4.dist-info/WHEEL
ndl_api-1.1.4.dist-info/top_level.txt
ndl_api-1.1.4.dist-info/RECORD
